jetpkg/__init__.py
jetpkg/tools.py
jetpkg-1.0.1.dist-info/METADATA
jetpkg-1.0.1.dist-info/WHEEL
jetpkg-1.0.1.dist-info/top_level.txt
jetpkg-1.0.1.dist-info/RECORD
